mydisct_solver/__init__.py
mydisct_solver/client.py
mydisct_solver/solver.py
mydisct_solver/types.py
mydisct_solver-1.0.2.dist-info/licenses/LICENSE
mydisct_solver-1.0.2.dist-info/METADATA
mydisct_solver-1.0.2.dist-info/WHEEL
mydisct_solver-1.0.2.dist-info/top_level.txt
mydisct_solver-1.0.2.dist-info/RECORD
