Metadata-Version: 2.4
Name: mydisct-solver
Version: 1.0.2
Summary: Official Python library for MyDisct Solver - Enterprise AI-Powered Captcha Solving Service with 20+ token types and 25+ image types
Home-page: https://github.com/mydisctsolver/MyDisct-Solver
Author: MyDisct Solver
Author-email: support@solver.mydisct.com
License: MIT
Project-URL: Bug Tracker, https://github.com/mydisctsolver/MyDisct-Solver/issues
Project-URL: Documentation, https://solver.mydisct.com/api-docs
Project-URL: Homepage, https://solver.mydisct.com
Keywords: captcha solver recaptcha hcaptcha hcaptcha-enterprise turnstile funcaptcha tencent-captcha tiktok-captcha geetest cloudflare mydisct automation bot bypass image-captcha token-captcha captcha-solving captcha-solver
Classifier: Development Status :: 5 - Production/Stable
Classifier: Intended Audience :: Developers
Classifier: License :: OSI Approved :: MIT License
Classifier: Programming Language :: Python :: 3
Classifier: Programming Language :: Python :: 3.7
Classifier: Programming Language :: Python :: 3.8
Classifier: Programming Language :: Python :: 3.9
Classifier: Programming Language :: Python :: 3.10
Classifier: Programming Language :: Python :: 3.11
Classifier: Programming Language :: Python :: 3.12
Classifier: Topic :: Software Development :: Libraries :: Python Modules
Classifier: Topic :: Internet :: WWW/HTTP
Classifier: Topic :: Security
Requires-Python: >=3.7
License-File: LICENSE
Requires-Dist: requests>=2.25.0
Dynamic: author
Dynamic: author-email
Dynamic: classifier
Dynamic: description
Dynamic: description-content-type
Dynamic: home-page
Dynamic: keywords
Dynamic: license
Dynamic: license-file
Dynamic: project-url
Dynamic: requires-dist
Dynamic: requires-python
Dynamic: summary
